LICENSE.txt
MANIFEST.in
README.md
setup.cfg
setup.py
examples/__init__.py
examples/tkip_ap.py
examples/wep_open_64.py
roguehostapd/__init__.py
roguehostapd/apctrl.py
roguehostapd/run.py
roguehostapd.egg-info/PKG-INFO
roguehostapd.egg-info/SOURCES.txt
roguehostapd.egg-info/dependency_links.txt
roguehostapd.egg-info/not-zip-safe
roguehostapd.egg-info/top_level.txt
roguehostapd/buildutil/__init__.py
roguehostapd/buildutil/__init__.pyc
roguehostapd/buildutil/build_files.py
roguehostapd/buildutil/build_files.pyc
roguehostapd/buildutil/buildcommon.py
roguehostapd/buildutil/buildcommon.pyc
roguehostapd/buildutil/buildexception.py
roguehostapd/buildutil/buildexception.pyc
roguehostapd/config/__init__.py
roguehostapd/config/__init__.pyc
roguehostapd/config/config.ini
roguehostapd/config/hostapd.conf
roguehostapd/config/hostapdconfig.py
roguehostapd/config/hostapdconfig.pyc
roguehostapd/hostapd-2_6/CONTRIBUTIONS
roguehostapd/hostapd-2_6/COPYING
roguehostapd/hostapd-2_6/README
roguehostapd/hostapd-2_6/hostapd/.config
roguehostapd/hostapd-2_6/hostapd/Android.mk
roguehostapd/hostapd-2_6/hostapd/ChangeLog
roguehostapd/hostapd-2_6/hostapd/Makefile
roguehostapd/hostapd-2_6/hostapd/README
roguehostapd/hostapd-2_6/hostapd/README-WPS
roguehostapd/hostapd-2_6/hostapd/android.config
roguehostapd/hostapd-2_6/hostapd/config_file.c
roguehostapd/hostapd-2_6/hostapd/config_file.h
roguehostapd/hostapd-2_6/hostapd/ctrl_iface.c
roguehostapd/hostapd-2_6/hostapd/ctrl_iface.h
roguehostapd/hostapd-2_6/hostapd/defconfig
roguehostapd/hostapd-2_6/hostapd/eap_register.c
roguehostapd/hostapd-2_6/hostapd/eap_register.h
roguehostapd/hostapd-2_6/hostapd/eap_testing.txt
roguehostapd/hostapd-2_6/hostapd/hapd_module_tests.c
roguehostapd/hostapd-2_6/hostapd/hlr_auc_gw.c
roguehostapd/hostapd-2_6/hostapd/hlr_auc_gw.milenage_db
roguehostapd/hostapd-2_6/hostapd/hlr_auc_gw.txt
roguehostapd/hostapd-2_6/hostapd/hostapd.8
roguehostapd/hostapd-2_6/hostapd/hostapd.accept
roguehostapd/hostapd-2_6/hostapd/hostapd.android.rc
roguehostapd/hostapd-2_6/hostapd/hostapd.conf
roguehostapd/hostapd-2_6/hostapd/hostapd.deny
roguehostapd/hostapd-2_6/hostapd/hostapd.eap_user
