Metadata-Version: 1.0
Name: roguehostapd
Version: 1.2.3
Summary: Hostapd wrapper for hostapd
Home-page: https://github.com/wifiphisher/roguehostapd
Author: Anakin
Author-email: UNKNOWN
License: UNKNOWN
Platform: UNKNOWN
